validatedata/__init__.py
validatedata/messages.py
validatedata/validatedata.py
validatedata/validator.py
validatedata-0.1.1.dist-info/LICENSE
validatedata-0.1.1.dist-info/METADATA
validatedata-0.1.1.dist-info/WHEEL
validatedata-0.1.1.dist-info/top_level.txt
validatedata-0.1.1.dist-info/RECORD
