Metadata-Version: 2.1
Name: validatedata
Version: 0.1.1
Summary: An easier way to validate data in python
Home-page: https://github.com/Edward-K1/validatedata
Author: Edward Kigozi
Author-email: edwardinbytes@gmail.com
License: MIT
Keywords: validate data validation
Platform: UNKNOWN
Classifier: Programming Language :: Python :: 3
Classifier: License :: OSI Approved :: MIT License
Classifier: Operating System :: OS Independent
Requires-Python: >=3.5
License-File: LICENSE
Requires-Dist: python-dateutil
